matterhorn/app.py
matterhorn/incoming.py
matterhorn/outgoing.py
matterhorn-0.0.1.dist-info/DESCRIPTION.rst
matterhorn-0.0.1.dist-info/METADATA
matterhorn-0.0.1.dist-info/metadata.json
matterhorn-0.0.1.dist-info/RECORD
matterhorn-0.0.1.dist-info/top_level.txt
matterhorn-0.0.1.dist-info/WHEEL
