Metadata-Version: 2.0
Name: matterhorn
Version: 0.0.1
Summary: Integration Framework for Mattermost
Home-page: UNKNOWN
Author: Jasper Schulz
Author-email: jasper.b.schulz@gmail.com
License: UNKNOWN
Platform: UNKNOWN
Classifier: Development Status :: 2 - Pre-Alpha
Classifier: Programming Language :: Python
Requires-Dist: Flask (==0.10.1)
Requires-Dist: requests (==2.9.1)
